README.rst
setup.py
ml3/__init__.py
ml3/ml3.py
ml3/ml3_backup.py
ml3.egg-info/PKG-INFO
ml3.egg-info/SOURCES.txt
ml3.egg-info/dependency_links.txt
ml3.egg-info/requires.txt
ml3.egg-info/top_level.txt